signal_scope/__init__.py
signal_scope/core.py
signal_scope/metrics.py
signal_scope/visualize.py
signal_scope-0.1.0.dist-info/METADATA
signal_scope-0.1.0.dist-info/WHEEL
signal_scope-0.1.0.dist-info/licenses/LICENSE
signal_scope-0.1.0.dist-info/RECORD
