Metadata-Version: 2.4
Name: signal-scope
Version: 0.1.0
Summary: A tiny (<200 line) Python tool for analyzing time-series signals: trends, volatility, drift, regime shifts, anomalies.
Project-URL: Homepage, https://github.com/rjsabouhi/signal-scope
Author-email: Ryan Sabouhi <your-email@example.com>
License: MIT License
License-File: LICENSE
Keywords: analysis,anomaly detection,signal processing,timeseries,volatility
Requires-Python: >=3.8
Requires-Dist: hatchling>=1.27.0
Requires-Dist: matplotlib
Requires-Dist: numpy
Requires-Dist: pandas
Requires-Dist: scipy
